collective.revisionmanager-1.2.3-py3.13-nspkg.pth
collective/revisionmanager/__init__.py
collective/revisionmanager/config.py
collective/revisionmanager/configure.zcml
collective/revisionmanager/interfaces.py
collective/revisionmanager/setuphandlers.py
collective/revisionmanager/statscache.py
collective/revisionmanager/testing.py
collective/revisionmanager/upgrades.py
collective/revisionmanager/upgrades.zcml
collective/revisionmanager/browser/__init__.py
collective/revisionmanager/browser/configure.zcml
collective/revisionmanager/browser/histories.pt
collective/revisionmanager/browser/revisionssettings.pt
collective/revisionmanager/browser/views.py
collective/revisionmanager/browser/static/.gitkeep
collective/revisionmanager/browser/static/revisionmanager.js
collective/revisionmanager/locales/collective.revisionmanager.pot
collective/revisionmanager/locales/manual.pot
collective/revisionmanager/locales/plone.pot
collective/revisionmanager/locales/de/LC_MESSAGES/collective.revisionmanager.mo
collective/revisionmanager/locales/de/LC_MESSAGES/collective.revisionmanager.po
collective/revisionmanager/locales/de/LC_MESSAGES/plone.mo
collective/revisionmanager/locales/de/LC_MESSAGES/plone.po
collective/revisionmanager/locales/en/LC_MESSAGES/collective.revisionmanager.mo
collective/revisionmanager/locales/en/LC_MESSAGES/collective.revisionmanager.po
collective/revisionmanager/locales/en/LC_MESSAGES/plone.mo
collective/revisionmanager/locales/en/LC_MESSAGES/plone.po
collective/revisionmanager/locales/es/LC_MESSAGES/collective.revisionmanager.mo
collective/revisionmanager/locales/es/LC_MESSAGES/collective.revisionmanager.po
collective/revisionmanager/locales/es/LC_MESSAGES/plone.mo
collective/revisionmanager/locales/es/LC_MESSAGES/plone.po
collective/revisionmanager/locales/nl/LC_MESSAGES/collective.revisionmanager.mo
collective/revisionmanager/locales/nl/LC_MESSAGES/collective.revisionmanager.po
collective/revisionmanager/locales/nl/LC_MESSAGES/plone.mo
collective.revisionmanager-1.2.3.dist-info/METADATA
collective.revisionmanager-1.2.3.dist-info/WHEEL
collective.revisionmanager-1.2.3.dist-info/entry_points.txt
collective.revisionmanager-1.2.3.dist-info/namespace_packages.txt
collective.revisionmanager-1.2.3.dist-info/top_level.txt
collective.revisionmanager-1.2.3.dist-info/RECORD
