Metadata-Version: 2.1
Name: collective.revisionmanager
Version: 1.2.3
Summary: Manage CMFEditions Histories
Home-page: https://pypi.python.org/pypi/collective.revisionmanager
Author: Thomas Schorr
Author-email: t_schorr@gmx.de
License: GPL version 2
Keywords: Python Plone
Classifier: Development Status :: 5 - Production/Stable
Classifier: Environment :: Web Environment
Classifier: Framework :: Plone
Classifier: Framework :: Plone :: 4.3
Classifier: Framework :: Plone :: 5.0
Classifier: Framework :: Plone :: 5.1
Classifier: Framework :: Plone :: 5.2
Classifier: Framework :: Plone :: 6.0
Classifier: Intended Audience :: System Administrators
Classifier: Programming Language :: Python
Classifier: Programming Language :: Python :: 2.7
Classifier: Programming Language :: Python :: 3.6
Classifier: Programming Language :: Python :: 3.7
Classifier: Programming Language :: Python :: 3.8
Classifier: Programming Language :: Python :: 3.9
Classifier: Operating System :: OS Independent
Classifier: License :: OSI Approved :: GNU General Public License v2 (GPLv2)
Requires-Dist: AccessControl
Requires-Dist: Acquisition
Requires-Dist: plone.api
Requires-Dist: plone.autoform
Requires-Dist: plone.batching
Requires-Dist: plone.protect
Requires-Dist: Products.CMFEditions>=2.2.16
Requires-Dist: Products.CMFPlone>=4.3
Requires-Dist: Products.CMFUid
Requires-Dist: Products.GenericSetup
Requires-Dist: setuptools
Requires-Dist: transaction
Requires-Dist: z3c.form
Requires-Dist: zope.component
Requires-Dist: zope.i18nmessageid
Requires-Dist: zope.interface
Requires-Dist: zope.publisher
Requires-Dist: zope.schema
Provides-Extra: test
Requires-Dist: plone.app.contenttypes; extra == "test"
Requires-Dist: plone.app.robotframework; extra == "test"
Requires-Dist: plone.app.testing; extra == "test"
Requires-Dist: plone.browserlayer; extra == "test"
Requires-Dist: plone.testing; extra == "test"
Requires-Dist: testfixtures; extra == "test"
